triangle_check/__init__.py
triangle_check/__main__.py
triangle_check-1.1.dist-info/CLA.md
triangle_check-1.1.dist-info/License.txt
triangle_check-1.1.dist-info/METADATA
triangle_check-1.1.dist-info/WHEEL
triangle_check-1.1.dist-info/entry_points.txt
triangle_check-1.1.dist-info/legal_notices.txt
triangle_check-1.1.dist-info/top_level.txt
triangle_check-1.1.dist-info/RECORD
