Metadata-Version: 2.1
Name: triangle-check
Version: 1.1
Summary: Triangle Check: scan iTunes backups for traces of compromise by Operation Triangulation
Home-page: https://github.com/KasperskyLab/triangle_check
Author: Kaspersky Lab
Author-email: triangulation@kaspersky.com
Project-URL: Bug Tracker, https://github.com/KasperskyLab/triangle_check/issues
Classifier: Programming Language :: Python :: 3
Classifier: License :: OSI Approved :: MIT License
Classifier: Operating System :: OS Independent
Requires-Python: >=3.8
License-File: License.txt
License-File: legal_notices.txt
License-File: CLA.md
Requires-Dist: setuptools (>=42)
Requires-Dist: colorama (==0.4.6)
Requires-Dist: pycryptodome (==3.17)
